MANIFEST.in
README.txt
setup.cfg
setup.py
adi/__init__.py
adi.workingcopyflag.egg-info/PKG-INFO
adi.workingcopyflag.egg-info/SOURCES.txt
adi.workingcopyflag.egg-info/dependency_links.txt
adi.workingcopyflag.egg-info/entry_points.txt
adi.workingcopyflag.egg-info/namespace_packages.txt
adi.workingcopyflag.egg-info/not-zip-safe
adi.workingcopyflag.egg-info/requires.txt
adi.workingcopyflag.egg-info/top_level.txt
adi/workingcopyflag/__init__.py
adi/workingcopyflag/configure.zcml
adi/workingcopyflag/interfaces.py
adi/workingcopyflag/profiles.zcml
adi/workingcopyflag/schemaextender.py
adi/workingcopyflag/setuphandlers.py
adi/workingcopyflag/subscriber.py
adi/workingcopyflag/profiles/adi.workingyopyflag.marker.txt
adi/workingcopyflag/profiles/catalog.xml
adi/workingcopyflag/profiles/metadata.xml
adi/workingcopyflag/profiles/portal_atct.xml