Metadata-Version: 1.0
Name: adi.workingcopyflag
Version: 1.4
Summary: Adds a field iHas workingcopy to archetypes and makes it available to collections for sorting.
Home-page: http://plone.org/products/adi.workingcopyflag
Author: Ida Ebkes
Author-email: contact@ida-ebkes.eu
License: GPL
Keywords: plone zope flag important iterate workingcopy index catalog collections topics
Platform: UNKNOWN
Classifier: Framework :: Plone
Classifier: Programming Language :: Python
Classifier: Topic :: Software Development :: Libraries :: Python Modules
